archassert/__init__.py
archassert/main.py
archassert-0.0.1.dist-info/LICENSE
archassert-0.0.1.dist-info/METADATA
archassert-0.0.1.dist-info/WHEEL
archassert-0.0.1.dist-info/RECORD
